[
  {
    "timestamp": "2026-05-17 11:06:37",
    "bomba_estado": 0.0,
    "tanque1_nivel": 100.0,
    "tanque2_nivel": 100.0,
    "tanque3_nivel": 100.0
  },
  {
    "timestamp": "2026-05-17 12:33:18",
    "bomba_estado": 0.0,
    "tanque1_nivel": 100.0,
    "tanque2_nivel": 100.0,
    "tanque3_nivel": 100.0
  },
  {
    "timestamp": "2026-05-17 21:29:00",
    "bomba_estado": 0.0,
    "tanque1_nivel": 100.0,
    "tanque2_nivel": 100.0,
    "tanque3_nivel": 100.0
  },
  {
    "timestamp": "2026-05-17 22:26:06",
    "bomba_estado": 0.0,
    "tanque1_nivel": 100.0,
    "tanque2_nivel": 100.0,
    "tanque3_nivel": 100.0
  },
  {
    "timestamp": "2026-05-17 23:27:44",
    "bomba_estado": 0.0,
    "tanque1_nivel": 100.0,
    "tanque2_nivel": 100.0,
    "tanque3_nivel": 100.0
  },
  {
    "timestamp": "2026-05-18 01:27:13",
    "bomba_estado": 0.0,
    "tanque1_nivel": 100.0,
    "tanque2_nivel": 100.0,
    "tanque3_nivel": 100.0
  },
  {
    "timestamp": "2026-05-18 05:41:46",
    "bomba_estado": 0.0,
    "tanque1_nivel": 100.0,
    "tanque2_nivel": 100.0,
    "tanque3_nivel": 100.0
  },
  {
    "timestamp": "2026-05-18 08:59:17",
    "bomba_estado": 0.0,
    "tanque1_nivel": 100.0,
    "tanque2_nivel": 100.0,
    "tanque3_nivel": 100.0
  },
  {
    "timestamp": "2026-05-18 12:34:12",
    "bomba_estado": 0.0,
    "tanque1_nivel": 100.0,
    "tanque2_nivel": 100.0,
    "tanque3_nivel": 100.0
  }
]